exist_client/__init__.py
exist_client/_exist_io_client/__init__.py
exist_client/_exist_io_client/api/__init__.py
exist_client/_exist_io_client/api/default/__init__.py
exist_client/_exist_io_client/api/default/access_token.py
exist_client/_exist_io_client/api/default/accounts_profile.py
exist_client/_exist_io_client/api/default/attribute_values_get.py
exist_client/_exist_io_client/api/default/attributes_acquire.py
exist_client/_exist_io_client/api/default/attributes_get.py
exist_client/_exist_io_client/api/default/attributes_update.py
exist_client/_exist_io_client/client.py
exist_client/_exist_io_client/errors.py
exist_client/_exist_io_client/models/__init__.py
exist_client/_exist_io_client/models/access_token_data.py
exist_client/_exist_io_client/models/attribute.py
exist_client/_exist_io_client/models/attribute_by_name.py
exist_client/_exist_io_client/models/attribute_by_template.py
exist_client/_exist_io_client/models/attribute_group.py
exist_client/_exist_io_client/models/attribute_value.py
exist_client/_exist_io_client/models/attribute_values_get_result.py
exist_client/_exist_io_client/models/attributes_acquire_result.py
exist_client/_exist_io_client/models/attributes_acquire_result_failed_item.py
exist_client/_exist_io_client/models/attributes_acquire_result_success_item.py
exist_client/_exist_io_client/models/attributes_get_result.py
exist_client/_exist_io_client/models/attributes_update_result.py
exist_client/_exist_io_client/models/attributes_update_result_failed_item.py
exist_client/_exist_io_client/models/date_value.py
exist_client/_exist_io_client/models/error_mixin.py
exist_client/_exist_io_client/models/paginated_response.py
exist_client/_exist_io_client/models/tokens.py
exist_client/_exist_io_client/models/user_profile.py
exist_client/_exist_io_client/types.py
exist_client/client.py
exist_client/models.py
exist_client/py.typed
exist_client-0.3.0.dist-info/METADATA
exist_client-0.3.0.dist-info/WHEEL
exist_client-0.3.0.dist-info/RECORD
